{
    "code": 0,
    "data": {
        "fund_chart": {
            "incomes": 15308107.293827,
            "outputs": 13559864.37434
        },
        "large_orders": [{
            "type": 1,
            "amount": 2.2134,
            "usd_price": 6472.33,
            "time": "2018-11-14 13:50:53"
        }, {
            "type": 1,
            "amount": 12.0396,
            "usd_price": 6471.91,
            "time": "2018-11-14 13:51:12"
        }, {
            "type": 1,
            "amount": 11.2758,
            "usd_price": 6470.68,
            "time": "2018-11-14 13:52:02"
        }, {
            "type": 1,
            "amount": 3.6734,
            "usd_price": 6471,
            "time": "2018-11-14 13:52:51"
        }, {
            "type": 1,
            "amount": 1.8542,
            "usd_price": 6470.57,
            "time": "2018-11-14 13:46:59"
        }, {
            "type": 1,
            "amount": 9.2295,
            "usd_price": 6474.17,
            "time": "2018-11-14 13:48:31"
        }, {
            "type": 2,
            "amount": 10.7943,
            "usd_price": 6474.21,
            "time": "2018-11-14 13:48:58"
        }, {
            "type": 1,
            "amount": 1.6727,
            "usd_price": 6474.1,
            "time": "2018-11-14 13:49:42"
        }, {
            "type": 2,
            "amount": 10.7444,
            "usd_price": 6469.1,
            "time": "2018-11-14 13:42:58"
        }, {
            "type": 2,
            "amount": 9.528,
            "usd_price": 6469.22,
            "time": "2018-11-14 13:43:23"
        }, {
            "type": 2,
            "amount": 10.7995,
            "usd_price": 6469.92,
            "time": "2018-11-14 13:43:42"
        }, {
            "type": 1,
            "amount": 8.1498,
            "usd_price": 6470.29,
            "time": "2018-11-14 13:44:41"
        }, {
            "type": 2,
            "amount": 1.9468,
            "usd_price": 6470.29,
            "time": "2018-11-14 13:44:44"
        }, {
            "type": 1,
            "amount": 4.629,
            "usd_price": 6466.04,
            "time": "2018-11-14 13:39:17"
        }, {
            "type": 1,
            "amount": 13.9526,
            "usd_price": 6465.9,
            "time": "2018-11-14 13:40:29"
        }, {
            "type": 1,
            "amount": 10.0575,
            "usd_price": 6465.78,
            "time": "2018-11-14 13:40:33"
        }, {
            "type": 1,
            "amount": 14.4983,
            "usd_price": 6465.85,
            "time": "2018-11-14 13:40:47"
        }, {
            "type": 2,
            "amount": 9.4619,
            "usd_price": 6465.83,
            "time": "2018-11-14 13:41:08"
        }, {
            "type": 1,
            "amount": 2.261,
            "usd_price": 6466.04,
            "time": "2018-11-14 13:41:35"
        }, {
            "type": 1,
            "amount": 7.7633,
            "usd_price": 6466.58,
            "time": "2018-11-14 13:42:20"
        }],
        "table_records": {
            "24hours": {
                "incomes": 20819844.338914,
                "outputs": 17748659.296663
            },
            "today": {
                "incomes": 15308107.293827,
                "outputs": 13559864.37434
            },
            "3min": {
                "incomes": 308107.293827,
                "outputs": 559864.37434
            },
            "10min": {
                "incomes": 5308107.293827,
                "outputs": 3559864.37434
            },
            "hour": {
                "incomes": 10308107.293827,
                "outputs": 10559864.37434
            },

        },
        "recent_1hour_minutes_records": [{
            "total_fund": 38346.398931,
            "incomes": 90780.658591,
            "outputs": 52434.25966,
            "time": "2018-11-14 12:57"
        }, {
            "total_fund": 3148.884706,
            "incomes": 5796.452997,
            "outputs": 2647.568291,
            "time": "2018-11-14 12:58"
        }, {
            "total_fund": -164480.730322,
            "incomes": 25082.553157,
            "outputs": 189563.283479,
            "time": "2018-11-14 12:59"
        }, {
            "total_fund": 57791.291141,
            "incomes": 129799.938093,
            "outputs": 72008.646952,
            "time": "2018-11-14 13:00"
        }, {
            "total_fund": 283236.136202,
            "incomes": 283578.673612,
            "outputs": 342.53741,
            "time": "2018-11-14 13:01"
        }, {
            "total_fund": 25536.298695,
            "incomes": 34775.512736,
            "outputs": 9239.214041,
            "time": "2018-11-14 13:02"
        }, {
            "total_fund": -92416.967157,
            "incomes": 2377.17494,
            "outputs": 94794.142097,
            "time": "2018-11-14 13:03"
        }, {
            "total_fund": 171.915546,
            "incomes": 548.700867,
            "outputs": 376.785321,
            "time": "2018-11-14 13:04"
        }, {
            "total_fund": 119158.941963,
            "incomes": 119458.82816,
            "outputs": 299.886197,
            "time": "2018-11-14 13:05"
        }, {
            "total_fund": -31076.393583,
            "incomes": 383.280687,
            "outputs": 31459.67427,
            "time": "2018-11-14 13:06"
        }, {
            "total_fund": -266730.26783401,
            "incomes": 19247.244741986,
            "outputs": 285977.512576,
            "time": "2018-11-14 13:07"
        }, {
            "total_fund": 64972.843073,
            "incomes": 64979.306912,
            "outputs": 6.463839,
            "time": "2018-11-14 13:08"
        }, {
            "total_fund": 73036.729959,
            "incomes": 79549.41539,
            "outputs": 6512.685431,
            "time": "2018-11-14 13:09"
        }, {
            "total_fund": -2939.12816,
            "incomes": 3362.32792,
            "outputs": 6301.45608,
            "time": "2018-11-14 13:10"
        }, {
            "total_fund": -96240.550955,
            "incomes": 7414.024293,
            "outputs": 103654.575248,
            "time": "2018-11-14 13:11"
        }, {
            "total_fund": -74779.637986,
            "incomes": 13.576641,
            "outputs": 74793.214627,
            "time": "2018-11-14 13:12"
        }, {
            "total_fund": 4819.909524,
            "incomes": 98343.838185,
            "outputs": 93523.928661,
            "time": "2018-11-14 13:13"
        }, {
            "total_fund": -39706.956905,
            "incomes": 18926.295597,
            "outputs": 58633.252502,
            "time": "2018-11-14 13:14"
        }, {
            "total_fund": 28201.77798,
            "incomes": 30364.905403,
            "outputs": 2163.127423,
            "time": "2018-11-14 13:15"
        }, {
            "total_fund": -350.359974,
            "incomes": 752.185097,
            "outputs": 1102.545071,
            "time": "2018-11-14 13:16"
        }, {
            "total_fund": 97700.65216,
            "incomes": 100285.80016,
            "outputs": 2585.148,
            "time": "2018-11-14 13:17"
        }, {
            "total_fund": -35750.703075,
            "incomes": 61729.349182,
            "outputs": 97480.052257,
            "time": "2018-11-14 13:18"
        }, {
            "total_fund": 81148.786314,
            "incomes": 84530.908238,
            "outputs": 3382.121924,
            "time": "2018-11-14 13:19"
        }, {
            "total_fund": 70918.832956,
            "incomes": 72870.4471,
            "outputs": 1951.614144,
            "time": "2018-11-14 13:20"
        }, {
            "total_fund": -302464.891688,
            "incomes": 55776.157315,
            "outputs": 358241.049003,
            "time": "2018-11-14 13:21"
        }, {
            "total_fund": -7146.449834,
            "incomes": 77915.986217,
            "outputs": 85062.436051,
            "time": "2018-11-14 13:22"
        }, {
            "total_fund": 50592.885633,
            "incomes": 53163.224073,
            "outputs": 2570.33844,
            "time": "2018-11-14 13:23"
        }, {
            "total_fund": 1068.217821,
            "incomes": 2666.818,
            "outputs": 1598.600179,
            "time": "2018-11-14 13:24"
        }, {
            "total_fund": -7836.250235,
            "incomes": 2771.872745,
            "outputs": 10608.12298,
            "time": "2018-11-14 13:25"
        }, {
            "total_fund": -83683.469946,
            "incomes": 1.29193,
            "outputs": 83684.761876,
            "time": "2018-11-14 13:26"
        }, {
            "total_fund": -52098.112020139,
            "incomes": 7882.6140258613,
            "outputs": 59980.726046,
            "time": "2018-11-14 13:27"
        }, {
            "total_fund": 32577.979581861,
            "incomes": 34315.950753861,
            "outputs": 1737.971172,
            "time": "2018-11-14 13:28"
        }, {
            "total_fund": -71604.943977,
            "incomes": 3839.867567,
            "outputs": 75444.811544,
            "time": "2018-11-14 13:29"
        }, {
            "total_fund": -82649.315527737,
            "incomes": 4263.7481912628,
            "outputs": 86913.063719,
            "time": "2018-11-14 13:30"
        }, {
            "total_fund": -120475.229634,
            "incomes": 1389.004962,
            "outputs": 121864.234596,
            "time": "2018-11-14 13:31"
        }, {
            "total_fund": 63477.991434,
            "incomes": 147695.6362,
            "outputs": 84217.644766,
            "time": "2018-11-14 13:32"
        }, {
            "total_fund": 22116.494538,
            "incomes": 108301.556453,
            "outputs": 86185.061915,
            "time": "2018-11-14 13:33"
        }, {
            "total_fund": -10.986485,
            "incomes": 68.50513,
            "outputs": 79.491615,
            "time": "2018-11-14 13:34"
        }, {
            "total_fund": -86870.833745,
            "incomes": 38112.536171,
            "outputs": 124983.369916,
            "time": "2018-11-14 13:35"
        }, {
            "total_fund": 55756.947972,
            "incomes": 166167.431157,
            "outputs": 110410.483185,
            "time": "2018-11-14 13:36"
        }, {
            "total_fund": 547.618326,
            "incomes": 755.156382,
            "outputs": 207.538056,
            "time": "2018-11-14 13:37"
        }, {
            "total_fund": -75789.995843,
            "incomes": 6462.805018,
            "outputs": 82252.800861,
            "time": "2018-11-14 13:38"
        }, {
            "total_fund": 29911.901402,
            "incomes": 30513.242192,
            "outputs": 601.34079,
            "time": "2018-11-14 13:39"
        }, {
            "total_fund": 240627.212303,
            "incomes": 251783.490345,
            "outputs": 11156.278042,
            "time": "2018-11-14 13:40"
        }, {
            "total_fund": -31545.203035,
            "incomes": 30022.432225,
            "outputs": 61567.63526,
            "time": "2018-11-14 13:41"
        }, {
            "total_fund": -102384.001139,
            "incomes": 70306.659437,
            "outputs": 172690.660576,
            "time": "2018-11-14 13:42"
        }, {
            "total_fund": -129589.081178,
            "incomes": 3982.731189,
            "outputs": 133571.812367,
            "time": "2018-11-14 13:43"
        }, {
            "total_fund": 36258.768698,
            "incomes": 53165.086128,
            "outputs": 16906.31743,
            "time": "2018-11-14 13:44"
        }, {
            "total_fund": -957.611337,
            "incomes": 1422.836357,
            "outputs": 2380.447694,
            "time": "2018-11-14 13:45"
        }, {
            "total_fund": 12453.133019,
            "incomes": 13747.854056,
            "outputs": 1294.721037,
            "time": "2018-11-14 13:46"
        }, {
            "total_fund": -540.408215,
            "incomes": 2204.430526,
            "outputs": 2744.838741,
            "time": "2018-11-14 13:47"
        }, {
            "total_fund": -11154.629884,
            "incomes": 62638.871334,
            "outputs": 73793.501218,
            "time": "2018-11-14 13:48"
        }, {
            "total_fund": 10068.08116,
            "incomes": 13307.636474,
            "outputs": 3239.555314,
            "time": "2018-11-14 13:49"
        }, {
            "total_fund": 20208.036551,
            "incomes": 25165.357382,
            "outputs": 4957.320831,
            "time": "2018-11-14 13:50"
        }, {
            "total_fund": 101128.950427,
            "incomes": 104041.584977,
            "outputs": 2912.63455,
            "time": "2018-11-14 13:51"
        }, {
            "total_fund": 120138.214693,
            "incomes": 120437.815144,
            "outputs": 299.600451,
            "time": "2018-11-14 13:52"
        }],
        "day_records": {
            "2018-11-10": -1021945.5839209,
            "2018-11-11": -2171456.3351792,
            "2018-11-12": 1179824.9587142,
            "2018-11-13": 2478004.1314984,
            "2018-11-14": 1748242.9194867
        },
        "trend_records": [{
            "total_fund": 643.455718,
            "incomes": 877.953704,
            "outputs": 234.497986,
            "time": "2018-11-14 08:00"
        }, {
            "total_fund": 14323.393888,
            "incomes": 15291.051327,
            "outputs": 967.657439,
            "time": "2018-11-14 08:01"
        }, {
            "total_fund": 7502.665648,
            "incomes": 34696.033352,
            "outputs": 27193.367704,
            "time": "2018-11-14 08:02"
        }, {
            "total_fund": 10194.11802,
            "incomes": 13821.97293,
            "outputs": 3627.85491,
            "time": "2018-11-14 08:03"
        }, {
            "total_fund": 22789.944709,
            "incomes": 37340.466142,
            "outputs": 14550.521433,
            "time": "2018-11-14 08:04"
        }, {
            "total_fund": -26514.619477,
            "incomes": 1488.940553,
            "outputs": 28003.56003,
            "time": "2018-11-14 08:05"
        }, {
            "total_fund": 17697.898432,
            "incomes": 34184.674374,
            "outputs": 16486.775942,
            "time": "2018-11-14 08:06"
        }, {
            "total_fund": -2185.030209,
            "incomes": 15672.434676,
            "outputs": 17857.464885,
            "time": "2018-11-14 08:07"
        }, {
            "total_fund": -3264.634131,
            "incomes": 15404.68915,
            "outputs": 18669.323281,
            "time": "2018-11-14 08:08"
        }, {
            "total_fund": 4706.58112,
            "incomes": 5586.323009,
            "outputs": 879.741889,
            "time": "2018-11-14 08:09"
        }, {
            "total_fund": -20039.993948,
            "incomes": 7762.250429,
            "outputs": 27802.244377,
            "time": "2018-11-14 08:10"
        }, {
            "total_fund": 22128.047492,
            "incomes": 22330.835489,
            "outputs": 202.787997,
            "time": "2018-11-14 08:11"
        }, {
            "total_fund": -20879.530334,
            "incomes": 754.988203,
            "outputs": 21634.518537,
            "time": "2018-11-14 08:12"
        }, {
            "total_fund": 3627.515639,
            "incomes": 6580.753134,
            "outputs": 2953.237495,
            "time": "2018-11-14 08:13"
        }, {
            "total_fund": -20681.584109,
            "incomes": 12612.76985,
            "outputs": 33294.353959,
            "time": "2018-11-14 08:14"
        }, {
            "total_fund": 24551.077104,
            "incomes": 25162.188552,
            "outputs": 611.111448,
            "time": "2018-11-14 08:15"
        }, {
            "total_fund": -4287.318609,
            "incomes": 12099.209746,
            "outputs": 16386.528355,
            "time": "2018-11-14 08:16"
        }, {
            "total_fund": -26902.936496,
            "incomes": 552.34544,
            "outputs": 27455.281936,
            "time": "2018-11-14 08:17"
        }, {
            "total_fund": 20288.171524,
            "incomes": 21015.505089,
            "outputs": 727.333565,
            "time": "2018-11-14 08:18"
        }, {
            "total_fund": -54859.263181,
            "incomes": 14976.750707,
            "outputs": 69836.013888,
            "time": "2018-11-14 08:19"
        }, {
            "total_fund": 758.64694899999,
            "incomes": 27689.817502,
            "outputs": 26931.170553,
            "time": "2018-11-14 08:20"
        }, {
            "total_fund": 15.521977,
            "incomes": 241.023236,
            "outputs": 225.501259,
            "time": "2018-11-14 08:21"
        }, {
            "total_fund": 17826.824628,
            "incomes": 18915.259145,
            "outputs": 1088.434517,
            "time": "2018-11-14 08:22"
        }, {
            "total_fund": 28111.547859,
            "incomes": 28623.458722,
            "outputs": 511.910863,
            "time": "2018-11-14 08:23"
        }, {
            "total_fund": 25142.481891,
            "incomes": 26891.867685,
            "outputs": 1749.385794,
            "time": "2018-11-14 08:24"
        }, {
            "total_fund": -77.043735,
            "incomes": 1481.673043,
            "outputs": 1558.716778,
            "time": "2018-11-14 08:25"
        }, {
            "total_fund": 44341.417449,
            "incomes": 44439.085178,
            "outputs": 97.667729,
            "time": "2018-11-14 08:26"
        }, {
            "total_fund": -16212.814608,
            "incomes": 16.820139,
            "outputs": 16229.634747,
            "time": "2018-11-14 08:27"
        }, {
            "total_fund": 1195.125181,
            "incomes": 1897.543726,
            "outputs": 702.418545,
            "time": "2018-11-14 08:28"
        }, {
            "total_fund": 20132.086128,
            "incomes": 20165.072824,
            "outputs": 32.986696,
            "time": "2018-11-14 08:29"
        }, {
            "total_fund": 3006.327288,
            "incomes": 3580.6848,
            "outputs": 574.357512,
            "time": "2018-11-14 08:30"
        }, {
            "total_fund": 21506.190100576,
            "incomes": 21506.836975576,
            "outputs": 0.646875,
            "time": "2018-11-14 08:31"
        }, {
            "total_fund": -8230.630782,
            "incomes": 7994.127715,
            "outputs": 16224.758497,
            "time": "2018-11-14 08:32"
        }, {
            "total_fund": -46443.114935,
            "incomes": 3867.984496,
            "outputs": 50311.099431,
            "time": "2018-11-14 08:33"
        }, {
            "total_fund": -14365.787504,
            "incomes": 2016.066715,
            "outputs": 16381.854219,
            "time": "2018-11-14 08:34"
        }, {
            "total_fund": 23582.680522,
            "incomes": 39752.034177,
            "outputs": 16169.353655,
            "time": "2018-11-14 08:35"
        }, {
            "total_fund": 24826.28432,
            "incomes": 25245.811736,
            "outputs": 419.527416,
            "time": "2018-11-14 08:36"
        }, {
            "total_fund": 34349.048452,
            "incomes": 34405.934585,
            "outputs": 56.886133,
            "time": "2018-11-14 08:37"
        }, {
            "total_fund": 6473.951999,
            "incomes": 21433.846349,
            "outputs": 14959.89435,
            "time": "2018-11-14 08:38"
        }, {
            "total_fund": 31351.577539,
            "incomes": 31354.810281,
            "outputs": 3.232742,
            "time": "2018-11-14 08:39"
        }, {
            "total_fund": -38173.473159,
            "incomes": 27503.154123,
            "outputs": 65676.627282,
            "time": "2018-11-14 08:40"
        }, {
            "total_fund": 34512.417036,
            "incomes": 35391.868824,
            "outputs": 879.451788,
            "time": "2018-11-14 08:41"
        }, {
            "total_fund": -24743.307769,
            "incomes": 5891.402909,
            "outputs": 30634.710678,
            "time": "2018-11-14 08:42"
        }, {
            "total_fund": 42353.402467,
            "incomes": 42727.791961,
            "outputs": 374.389494,
            "time": "2018-11-14 08:43"
        }, {
            "total_fund": 39634.18339,
            "incomes": 40669.446142,
            "outputs": 1035.262752,
            "time": "2018-11-14 08:44"
        }, {
            "total_fund": 41525.398601,
            "incomes": 42929.248296,
            "outputs": 1403.849695,
            "time": "2018-11-14 08:45"
        }, {
            "total_fund": 10377.465144,
            "incomes": 23727.494901,
            "outputs": 13350.029757,
            "time": "2018-11-14 08:46"
        }, {
            "total_fund": 14806.817362,
            "incomes": 15527.820405,
            "outputs": 721.003043,
            "time": "2018-11-14 08:47"
        }, {
            "total_fund": -2415.213023,
            "incomes": 36.210575,
            "outputs": 2451.423598,
            "time": "2018-11-14 08:48"
        }, {
            "total_fund": -3911.633616,
            "incomes": 16652.549803,
            "outputs": 20564.183419,
            "time": "2018-11-14 08:49"
        }, {
            "total_fund": -23079.259158,
            "incomes": 3146.435764,
            "outputs": 26225.694922,
            "time": "2018-11-14 08:50"
        }, {
            "total_fund": 5413.318574,
            "incomes": 19556.050501,
            "outputs": 14142.731927,
            "time": "2018-11-14 08:51"
        }, {
            "total_fund": 50832.932279345,
            "incomes": 51652.878733345,
            "outputs": 819.946454,
            "time": "2018-11-14 08:52"
        }, {
            "total_fund": -5119.456877,
            "incomes": 15576.455158,
            "outputs": 20695.912035,
            "time": "2018-11-14 08:53"
        }, {
            "total_fund": -11806.65931,
            "incomes": 3102.702225,
            "outputs": 14909.361535,
            "time": "2018-11-14 08:54"
        }, {
            "total_fund": -14294.136817,
            "incomes": 12249.168017,
            "outputs": 26543.304834,
            "time": "2018-11-14 08:55"
        }, {
            "total_fund": -13026.786034,
            "incomes": 1572.610421,
            "outputs": 14599.396455,
            "time": "2018-11-14 08:56"
        }, {
            "total_fund": 3330.384107,
            "incomes": 4959.815327,
            "outputs": 1629.43122,
            "time": "2018-11-14 08:57"
        }, {
            "total_fund": -327.149372,
            "incomes": 13590.045045,
            "outputs": 13917.194417,
            "time": "2018-11-14 08:58"
        }, {
            "total_fund": -33214.561493,
            "incomes": 1163.455425,
            "outputs": 34378.016918,
            "time": "2018-11-14 08:59"
        }, {
            "total_fund": 14538.612568,
            "incomes": 28966.951403,
            "outputs": 14428.338835,
            "time": "2018-11-14 09:00"
        }, {
            "total_fund": 14232.602045,
            "incomes": 15005.655193,
            "outputs": 773.053148,
            "time": "2018-11-14 09:01"
        }, {
            "total_fund": -852.902976,
            "incomes": 15912.66754,
            "outputs": 16765.570516,
            "time": "2018-11-14 09:02"
        }, {
            "total_fund": -7368.288631,
            "incomes": 27391.859466,
            "outputs": 34760.148097,
            "time": "2018-11-14 09:03"
        }, {
            "total_fund": 7160.100561,
            "incomes": 11152.231275,
            "outputs": 3992.130714,
            "time": "2018-11-14 09:04"
        }, {
            "total_fund": 2131.469068,
            "incomes": 2618.8076,
            "outputs": 487.338532,
            "time": "2018-11-14 09:05"
        }, {
            "total_fund": -19852.599041,
            "incomes": 13968.696864,
            "outputs": 33821.295905,
            "time": "2018-11-14 09:06"
        }, {
            "total_fund": -12396.052127,
            "incomes": 4118.29184,
            "outputs": 16514.343967,
            "time": "2018-11-14 09:07"
        }, {
            "total_fund": 10698.206745,
            "incomes": 12797.921591,
            "outputs": 2099.714846,
            "time": "2018-11-14 09:08"
        }, {
            "total_fund": 2069.056622,
            "incomes": 2876.309759,
            "outputs": 807.253137,
            "time": "2018-11-14 09:09"
        }, {
            "total_fund": -6881.856864,
            "incomes": 2692.262574,
            "outputs": 9574.119438,
            "time": "2018-11-14 09:10"
        }, {
            "total_fund": 40950.646769,
            "incomes": 41097.984654,
            "outputs": 147.337885,
            "time": "2018-11-14 09:11"
        }, {
            "total_fund": -803.380926,
            "incomes": 16040.32926,
            "outputs": 16843.710186,
            "time": "2018-11-14 09:12"
        }, {
            "total_fund": -2507.786558,
            "incomes": 1.292278,
            "outputs": 2509.078836,
            "time": "2018-11-14 09:13"
        }, {
            "total_fund": 1346.394406,
            "incomes": 14626.658849,
            "outputs": 13280.264443,
            "time": "2018-11-14 09:14"
        }, {
            "total_fund": 39.428043,
            "incomes": 131.828002,
            "outputs": 92.399959,
            "time": "2018-11-14 09:15"
        }, {
            "total_fund": -23249.839652,
            "incomes": 8308.180754,
            "outputs": 31558.020406,
            "time": "2018-11-14 09:16"
        }, {
            "total_fund": -52125.203705,
            "incomes": 1351.592402,
            "outputs": 53476.796107,
            "time": "2018-11-14 09:17"
        }, {
            "total_fund": -11928.038773,
            "incomes": 9034.732042,
            "outputs": 20962.770815,
            "time": "2018-11-14 09:18"
        }, {
            "total_fund": -11850.202434,
            "incomes": 13439.487518,
            "outputs": 25289.689952,
            "time": "2018-11-14 09:19"
        }, {
            "total_fund": 7474.127772,
            "incomes": 19007.68388,
            "outputs": 11533.556108,
            "time": "2018-11-14 09:20"
        }, {
            "total_fund": -1663.634385,
            "incomes": 2347.124153,
            "outputs": 4010.758538,
            "time": "2018-11-14 09:21"
        }, {
            "total_fund": 19922.300258,
            "incomes": 35802.158399,
            "outputs": 15879.858141,
            "time": "2018-11-14 09:22"
        }, {
            "total_fund": 13725.744404,
            "incomes": 15329.65661,
            "outputs": 1603.912206,
            "time": "2018-11-14 09:23"
        }, {
            "total_fund": 3243.58957,
            "incomes": 7321.054039,
            "outputs": 4077.464469,
            "time": "2018-11-14 09:24"
        }, {
            "total_fund": -1428.194045,
            "incomes": 2693.217975,
            "outputs": 4121.41202,
            "time": "2018-11-14 09:25"
        }, {
            "total_fund": -71.125137999996,
            "incomes": 31775.014304,
            "outputs": 31846.139442,
            "time": "2018-11-14 09:26"
        }, {
            "total_fund": 18163.56053,
            "incomes": 19295.753231,
            "outputs": 1132.192701,
            "time": "2018-11-14 09:27"
        }, {
            "total_fund": -617.552733,
            "incomes": 1759.914644,
            "outputs": 2377.467377,
            "time": "2018-11-14 09:28"
        }, {
            "total_fund": -11546.975328,
            "incomes": 23574.306319,
            "outputs": 35121.281647,
            "time": "2018-11-14 09:29"
        }, {
            "total_fund": 49913.886797,
            "incomes": 71304.338117,
            "outputs": 21390.45132,
            "time": "2018-11-14 09:30"
        }, {
            "total_fund": 303.764434,
            "incomes": 639.766701,
            "outputs": 336.002267,
            "time": "2018-11-14 09:31"
        }, {
            "total_fund": -19746.306279,
            "incomes": 843.30191,
            "outputs": 20589.608189,
            "time": "2018-11-14 09:32"
        }, {
            "total_fund": -27243.78857509,
            "incomes": 8298.55389491,
            "outputs": 35542.34247,
            "time": "2018-11-14 09:33"
        }, {
            "total_fund": 89.722734000003,
            "incomes": 28942.457139,
            "outputs": 28852.734405,
            "time": "2018-11-14 09:34"
        }, {
            "total_fund": 5014.03455,
            "incomes": 21053.406693,
            "outputs": 16039.372143,
            "time": "2018-11-14 09:35"
        }, {
            "total_fund": 12441.089031,
            "incomes": 17420.392856,
            "outputs": 4979.303825,
            "time": "2018-11-14 09:36"
        }, {
            "total_fund": 4972.649621,
            "incomes": 7296.783318,
            "outputs": 2324.133697,
            "time": "2018-11-14 09:37"
        }, {
            "total_fund": -20116.39732,
            "incomes": 20798.705617,
            "outputs": 40915.102937,
            "time": "2018-11-14 09:38"
        }, {
            "total_fund": -22255.062579,
            "incomes": 11366.081769,
            "outputs": 33621.144348,
            "time": "2018-11-14 09:39"
        }, {
            "total_fund": -6535.982549,
            "incomes": 6353.42334,
            "outputs": 12889.405889,
            "time": "2018-11-14 09:40"
        }, {
            "total_fund": 27514.030976,
            "incomes": 34591.796173,
            "outputs": 7077.765197,
            "time": "2018-11-14 09:41"
        }, {
            "total_fund": 31058.144651,
            "incomes": 50360.727504,
            "outputs": 19302.582853,
            "time": "2018-11-14 09:42"
        }, {
            "total_fund": 22841.89197,
            "incomes": 51303.409554,
            "outputs": 28461.517584,
            "time": "2018-11-14 09:43"
        }, {
            "total_fund": 5470.104444,
            "incomes": 23977.918961,
            "outputs": 18507.814517,
            "time": "2018-11-14 09:44"
        }, {
            "total_fund": 22639.943455,
            "incomes": 24235.543954,
            "outputs": 1595.600499,
            "time": "2018-11-14 09:45"
        }, {
            "total_fund": -14234.576802,
            "incomes": 502.965394,
            "outputs": 14737.542196,
            "time": "2018-11-14 09:46"
        }, {
            "total_fund": 2868.620282,
            "incomes": 20385.605355,
            "outputs": 17516.985073,
            "time": "2018-11-14 09:47"
        }, {
            "total_fund": 4930.890427,
            "incomes": 14323.449405,
            "outputs": 9392.558978,
            "time": "2018-11-14 09:48"
        }, {
            "total_fund": -8384.617696,
            "incomes": 149.218029,
            "outputs": 8533.835725,
            "time": "2018-11-14 09:49"
        }, {
            "total_fund": -16990.980028,
            "incomes": 510.213468,
            "outputs": 17501.193496,
            "time": "2018-11-14 09:50"
        }, {
            "total_fund": 767.31881300001,
            "incomes": 17187.056298,
            "outputs": 16419.737485,
            "time": "2018-11-14 09:51"
        }, {
            "total_fund": 12613.364509,
            "incomes": 15218.959427,
            "outputs": 2605.594918,
            "time": "2018-11-14 09:52"
        }, {
            "total_fund": -14482.464113,
            "incomes": 5513.37874,
            "outputs": 19995.842853,
            "time": "2018-11-14 09:53"
        }, {
            "total_fund": 3785.441457,
            "incomes": 4260.39011,
            "outputs": 474.948653,
            "time": "2018-11-14 09:54"
        }, {
            "total_fund": 49517.869416,
            "incomes": 50084.586114,
            "outputs": 566.716698,
            "time": "2018-11-14 09:55"
        }, {
            "total_fund": 18953.071079,
            "incomes": 23695.687059,
            "outputs": 4742.61598,
            "time": "2018-11-14 09:56"
        }, {
            "total_fund": 8544.648355,
            "incomes": 9492.89659,
            "outputs": 948.248235,
            "time": "2018-11-14 09:57"
        }, {
            "total_fund": -18427.382702,
            "incomes": 12271.218114,
            "outputs": 30698.600816,
            "time": "2018-11-14 09:58"
        }, {
            "total_fund": 21050.727967,
            "incomes": 23775.780642,
            "outputs": 2725.052675,
            "time": "2018-11-14 09:59"
        }, {
            "total_fund": -266.017876,
            "incomes": 23832.583035,
            "outputs": 24098.600911,
            "time": "2018-11-14 10:00"
        }, {
            "total_fund": 3747.275446,
            "incomes": 25552.531377,
            "outputs": 21805.255931,
            "time": "2018-11-14 10:01"
        }, {
            "total_fund": 14789.581383,
            "incomes": 17595.884355,
            "outputs": 2806.302972,
            "time": "2018-11-14 10:02"
        }, {
            "total_fund": 7811.507498,
            "incomes": 14376.899025,
            "outputs": 6565.391527,
            "time": "2018-11-14 10:03"
        }, {
            "total_fund": -622.592301,
            "incomes": 2730.194158,
            "outputs": 3352.786459,
            "time": "2018-11-14 10:04"
        }, {
            "total_fund": -32350.67263,
            "incomes": 5171.908057,
            "outputs": 37522.580687,
            "time": "2018-11-14 10:05"
        }, {
            "total_fund": -18475.283134,
            "incomes": 39700.917576,
            "outputs": 58176.20071,
            "time": "2018-11-14 10:06"
        }, {
            "total_fund": 19659.309167,
            "incomes": 48151.348825,
            "outputs": 28492.039658,
            "time": "2018-11-14 10:07"
        }, {
            "total_fund": -2842.538176,
            "incomes": 33155.598239,
            "outputs": 35998.136415,
            "time": "2018-11-14 10:08"
        }, {
            "total_fund": 20740.667824,
            "incomes": 21636.313292,
            "outputs": 895.645468,
            "time": "2018-11-14 10:09"
        }, {
            "total_fund": 38584.877536,
            "incomes": 39787.002297,
            "outputs": 1202.124761,
            "time": "2018-11-14 10:10"
        }, {
            "total_fund": 17668.448093,
            "incomes": 18067.337487,
            "outputs": 398.889394,
            "time": "2018-11-14 10:11"
        }, {
            "total_fund": -29901.457245411,
            "incomes": 3586.3097375885,
            "outputs": 33487.766983,
            "time": "2018-11-14 10:12"
        }, {
            "total_fund": 49454.042465,
            "incomes": 52669.524366,
            "outputs": 3215.481901,
            "time": "2018-11-14 10:13"
        }, {
            "total_fund": 4814.600383,
            "incomes": 13990.730882,
            "outputs": 9176.130499,
            "time": "2018-11-14 10:14"
        }, {
            "total_fund": 16382.731241,
            "incomes": 35334.213987,
            "outputs": 18951.482746,
            "time": "2018-11-14 10:15"
        }, {
            "total_fund": 33727.754861,
            "incomes": 34632.139748,
            "outputs": 904.384887,
            "time": "2018-11-14 10:16"
        }, {
            "total_fund": -16878.438848,
            "incomes": 2823.756822,
            "outputs": 19702.19567,
            "time": "2018-11-14 10:17"
        }, {
            "total_fund": -19068.862838,
            "incomes": 227.275988,
            "outputs": 19296.138826,
            "time": "2018-11-14 10:18"
        }, {
            "total_fund": -9435.45991,
            "incomes": 18334.338886,
            "outputs": 27769.798796,
            "time": "2018-11-14 10:19"
        }, {
            "total_fund": 4971.522667,
            "incomes": 5256.933792,
            "outputs": 285.411125,
            "time": "2018-11-14 10:20"
        }, {
            "total_fund": 23020.406659,
            "incomes": 23122.413173,
            "outputs": 102.006514,
            "time": "2018-11-14 10:21"
        }, {
            "total_fund": -28548.384946,
            "incomes": 4669.021698,
            "outputs": 33217.406644,
            "time": "2018-11-14 10:22"
        }, {
            "total_fund": -22571.473701,
            "incomes": 17926.278181,
            "outputs": 40497.751882,
            "time": "2018-11-14 10:23"
        }, {
            "total_fund": 33301.12512149,
            "incomes": 34181.14452649,
            "outputs": 880.019405,
            "time": "2018-11-14 10:24"
        }, {
            "total_fund": -14137.28402351,
            "incomes": 1594.16786849,
            "outputs": 15731.451892,
            "time": "2018-11-14 10:25"
        }, {
            "total_fund": 27924.670566,
            "incomes": 29658.031305,
            "outputs": 1733.360739,
            "time": "2018-11-14 10:26"
        }, {
            "total_fund": 47011.177066,
            "incomes": 62689.34195,
            "outputs": 15678.164884,
            "time": "2018-11-14 10:27"
        }, {
            "total_fund": -7887.608499,
            "incomes": 9443.313463,
            "outputs": 17330.921962,
            "time": "2018-11-14 10:28"
        }, {
            "total_fund": 2126.33401,
            "incomes": 19076.219133,
            "outputs": 16949.885123,
            "time": "2018-11-14 10:29"
        }, {
            "total_fund": 17192.144905,
            "incomes": 17925.543884,
            "outputs": 733.398979,
            "time": "2018-11-14 10:30"
        }, {
            "total_fund": -2056.548543,
            "incomes": 10555.2579,
            "outputs": 12611.806443,
            "time": "2018-11-14 10:31"
        }, {
            "total_fund": 19876.527464,
            "incomes": 31276.291796,
            "outputs": 11399.764332,
            "time": "2018-11-14 10:32"
        }, {
            "total_fund": 30004.634288,
            "incomes": 32045.569029,
            "outputs": 2040.934741,
            "time": "2018-11-14 10:33"
        }, {
            "total_fund": -26395.036711,
            "incomes": 6908.560582,
            "outputs": 33303.597293,
            "time": "2018-11-14 10:34"
        }, {
            "total_fund": -14165.771741,
            "incomes": 6228.434175,
            "outputs": 20394.205916,
            "time": "2018-11-14 10:35"
        }, {
            "total_fund": -51024.072566,
            "incomes": 7444.612984,
            "outputs": 58468.68555,
            "time": "2018-11-14 10:36"
        }, {
            "total_fund": 17017.826209,
            "incomes": 18493.859277,
            "outputs": 1476.033068,
            "time": "2018-11-14 10:37"
        }, {
            "total_fund": -8232.59728,
            "incomes": 10236.691266,
            "outputs": 18469.288546,
            "time": "2018-11-14 10:38"
        }, {
            "total_fund": 14314.652413,
            "incomes": 15430.919291,
            "outputs": 1116.266878,
            "time": "2018-11-14 10:39"
        }, {
            "total_fund": 29306.303233,
            "incomes": 42123.720356,
            "outputs": 12817.417123,
            "time": "2018-11-14 10:40"
        }, {
            "total_fund": -14634.741187455,
            "incomes": 11344.907178,
            "outputs": 25979.648365455,
            "time": "2018-11-14 10:41"
        }, {
            "total_fund": 5344.744099,
            "incomes": 7990.6445,
            "outputs": 2645.900401,
            "time": "2018-11-14 10:42"
        }, {
            "total_fund": 8995.785114,
            "incomes": 29702.373379,
            "outputs": 20706.588265,
            "time": "2018-11-14 10:43"
        }, {
            "total_fund": -12779.570985,
            "incomes": 6917.170398,
            "outputs": 19696.741383,
            "time": "2018-11-14 10:44"
        }, {
            "total_fund": 46751.140252,
            "incomes": 49721.08561,
            "outputs": 2969.945358,
            "time": "2018-11-14 10:45"
        }, {
            "total_fund": 2161.36109,
            "incomes": 4306.051583,
            "outputs": 2144.690493,
            "time": "2018-11-14 10:46"
        }, {
            "total_fund": -8488.25706,
            "incomes": 134.35634,
            "outputs": 8622.6134,
            "time": "2018-11-14 10:47"
        }, {
            "total_fund": -23073.593427,
            "incomes": 16000.828602,
            "outputs": 39074.422029,
            "time": "2018-11-14 10:48"
        }, {
            "total_fund": 33472.095037,
            "incomes": 47862.695357,
            "outputs": 14390.60032,
            "time": "2018-11-14 10:49"
        }, {
            "total_fund": -17773.642627,
            "incomes": 13469.149795,
            "outputs": 31242.792422,
            "time": "2018-11-14 10:50"
        }, {
            "total_fund": -141.411454,
            "incomes": 380.401956,
            "outputs": 521.81341,
            "time": "2018-11-14 10:51"
        }, {
            "total_fund": -1420.200445,
            "incomes": 233.796149,
            "outputs": 1653.996594,
            "time": "2018-11-14 10:52"
        }, {
            "total_fund": 33607.590682,
            "incomes": 34199.189018,
            "outputs": 591.598336,
            "time": "2018-11-14 10:53"
        }, {
            "total_fund": -230.595733,
            "incomes": 0,
            "outputs": 230.595733,
            "time": "2018-11-14 10:54"
        }, {
            "total_fund": -12827.644653,
            "incomes": 1436.54832,
            "outputs": 14264.192973,
            "time": "2018-11-14 10:55"
        }, {
            "total_fund": -522.504785,
            "incomes": 0,
            "outputs": 522.504785,
            "time": "2018-11-14 10:56"
        }, {
            "total_fund": -10028.474469,
            "incomes": 1778.208228,
            "outputs": 11806.682697,
            "time": "2018-11-14 10:57"
        }, {
            "total_fund": -2133.286527,
            "incomes": 13105.878724,
            "outputs": 15239.165251,
            "time": "2018-11-14 10:58"
        }, {
            "total_fund": 14798.185828,
            "incomes": 16975.809712,
            "outputs": 2177.623884,
            "time": "2018-11-14 10:59"
        }, {
            "total_fund": 2903.689375,
            "incomes": 36801.665855,
            "outputs": 33897.97648,
            "time": "2018-11-14 11:00"
        }, {
            "total_fund": -21241.765988,
            "incomes": 2319.246371,
            "outputs": 23561.012359,
            "time": "2018-11-14 11:01"
        }, {
            "total_fund": -2950.071655,
            "incomes": 28885.479791,
            "outputs": 31835.551446,
            "time": "2018-11-14 11:02"
        }, {
            "total_fund": 3826.261493,
            "incomes": 5082.703033,
            "outputs": 1256.44154,
            "time": "2018-11-14 11:03"
        }, {
            "total_fund": -2262.754303,
            "incomes": 1495.193649,
            "outputs": 3757.947952,
            "time": "2018-11-14 11:04"
        }, {
            "total_fund": 29812.006077,
            "incomes": 30159.069339,
            "outputs": 347.063262,
            "time": "2018-11-14 11:05"
        }, {
            "total_fund": 6008.463931,
            "incomes": 7641.2095,
            "outputs": 1632.745569,
            "time": "2018-11-14 11:06"
        }, {
            "total_fund": 3792.557264,
            "incomes": 8219.858548,
            "outputs": 4427.301284,
            "time": "2018-11-14 11:07"
        }, {
            "total_fund": -25484.58391,
            "incomes": 41376.696141,
            "outputs": 66861.280051,
            "time": "2018-11-14 11:08"
        }, {
            "total_fund": -2083.809512,
            "incomes": 7592.464617,
            "outputs": 9676.274129,
            "time": "2018-11-14 11:10"
        }, {
            "total_fund": 27685.683921,
            "incomes": 51617.017723,
            "outputs": 23931.333802,
            "time": "2018-11-14 11:11"
        }, {
            "total_fund": 23294.841605,
            "incomes": 59463.946042,
            "outputs": 36169.104437,
            "time": "2018-11-14 11:12"
        }, {
            "total_fund": -18420.388783264,
            "incomes": 12617.028758736,
            "outputs": 31037.417542,
            "time": "2018-11-14 11:13"
        }, {
            "total_fund": 8669.609005,
            "incomes": 9518.198234,
            "outputs": 848.589229,
            "time": "2018-11-14 11:14"
        }, {
            "total_fund": 3576.466788,
            "incomes": 27461.412066,
            "outputs": 23884.945278,
            "time": "2018-11-14 11:15"
        }, {
            "total_fund": 20437.73997,
            "incomes": 21114.023203,
            "outputs": 676.283233,
            "time": "2018-11-14 11:16"
        }, {
            "total_fund": 40900.542029,
            "incomes": 51945.300697,
            "outputs": 11044.758668,
            "time": "2018-11-14 11:17"
        }, {
            "total_fund": 12857.370853,
            "incomes": 15909.659031,
            "outputs": 3052.288178,
            "time": "2018-11-14 11:18"
        }, {
            "total_fund": 19713.732797,
            "incomes": 20192.259264,
            "outputs": 478.526467,
            "time": "2018-11-14 11:19"
        }, {
            "total_fund": 75178.609712564,
            "incomes": 75703.653063564,
            "outputs": 525.043351,
            "time": "2018-11-14 11:20"
        }, {
            "total_fund": 5350.745691,
            "incomes": 21597.939846,
            "outputs": 16247.194155,
            "time": "2018-11-14 11:21"
        }, {
            "total_fund": 5014.310475,
            "incomes": 10280.750614,
            "outputs": 5266.440139,
            "time": "2018-11-14 11:22"
        }, {
            "total_fund": 12377.930169,
            "incomes": 26895.954832,
            "outputs": 14518.024663,
            "time": "2018-11-14 11:23"
        }, {
            "total_fund": -7691.060057,
            "incomes": 17345.091289,
            "outputs": 25036.151346,
            "time": "2018-11-14 11:24"
        }, {
            "total_fund": 7865.6088141692,
            "incomes": 33665.315773169,
            "outputs": 25799.706959,
            "time": "2018-11-14 11:25"
        }, {
            "total_fund": 11194.533226,
            "incomes": 42558.461374,
            "outputs": 31363.928148,
            "time": "2018-11-14 11:26"
        }, {
            "total_fund": 941.846704,
            "incomes": 26958.574109,
            "outputs": 26016.727405,
            "time": "2018-11-14 11:27"
        }, {
            "total_fund": 42201.161256,
            "incomes": 69443.361135,
            "outputs": 27242.199879,
            "time": "2018-11-14 11:28"
        }, {
            "total_fund": -11728.64158,
            "incomes": 2582.196442,
            "outputs": 14310.838022,
            "time": "2018-11-14 11:29"
        }, {
            "total_fund": -3360.7028250621,
            "incomes": 718.008294,
            "outputs": 4078.7111190621,
            "time": "2018-11-14 11:30"
        }, {
            "total_fund": 21543.780383047,
            "incomes": 53265.265060047,
            "outputs": 31721.484677,
            "time": "2018-11-14 11:31"
        }, {
            "total_fund": 9905.08882,
            "incomes": 12909.935221,
            "outputs": 3004.846401,
            "time": "2018-11-14 11:32"
        }, {
            "total_fund": 19094.708002,
            "incomes": 23396.10622,
            "outputs": 4301.398218,
            "time": "2018-11-14 11:33"
        }, {
            "total_fund": -9616.304212,
            "incomes": 42171.235575,
            "outputs": 51787.539787,
            "time": "2018-11-14 11:34"
        }, {
            "total_fund": -35528.732573,
            "incomes": 17418.074075,
            "outputs": 52946.806648,
            "time": "2018-11-14 11:35"
        }, {
            "total_fund": -34940.193932,
            "incomes": 3691.189436,
            "outputs": 38631.383368,
            "time": "2018-11-14 11:36"
        }, {
            "total_fund": 1984.043007,
            "incomes": 17048.973946,
            "outputs": 15064.930939,
            "time": "2018-11-14 11:37"
        }, {
            "total_fund": 41973.388726,
            "incomes": 62778.108515,
            "outputs": 20804.719789,
            "time": "2018-11-14 11:38"
        }, {
            "total_fund": -20892.658173,
            "incomes": 11982.236934,
            "outputs": 32874.895107,
            "time": "2018-11-14 11:39"
        }, {
            "total_fund": 4528.082955,
            "incomes": 8722.112334,
            "outputs": 4194.029379,
            "time": "2018-11-14 11:40"
        }, {
            "total_fund": 71912.650578,
            "incomes": 120052.77445,
            "outputs": 48140.123872,
            "time": "2018-11-14 11:41"
        }, {
            "total_fund": 24196.652049,
            "incomes": 28450.360061,
            "outputs": 4253.708012,
            "time": "2018-11-14 11:42"
        }, {
            "total_fund": -141289.645528,
            "incomes": 3593.110542,
            "outputs": 144882.75607,
            "time": "2018-11-14 11:43"
        }, {
            "total_fund": -56739.17935,
            "incomes": 8.398418,
            "outputs": 56747.577768,
            "time": "2018-11-14 11:44"
        }, {
            "total_fund": 96522.408326,
            "incomes": 100390.344502,
            "outputs": 3867.936176,
            "time": "2018-11-14 11:45"
        }, {
            "total_fund": 136372.505943,
            "incomes": 139211.328735,
            "outputs": 2838.822792,
            "time": "2018-11-14 11:46"
        }, {
            "total_fund": 1561.289768,
            "incomes": 60679.16106,
            "outputs": 59117.871292,
            "time": "2018-11-14 11:47"
        }, {
            "total_fund": 58334.974425,
            "incomes": 60361.980286,
            "outputs": 2027.005861,
            "time": "2018-11-14 11:48"
        }, {
            "total_fund": -64077.832915,
            "incomes": 8182.597925,
            "outputs": 72260.43084,
            "time": "2018-11-14 11:49"
        }, {
            "total_fund": -146291.542664,
            "incomes": 3408.618786,
            "outputs": 149700.16145,
            "time": "2018-11-14 11:50"
        }, {
            "total_fund": 168848.755951,
            "incomes": 173266.919931,
            "outputs": 4418.16398,
            "time": "2018-11-14 11:51"
        }, {
            "total_fund": 235243.719224,
            "incomes": 239866.457719,
            "outputs": 4622.738495,
            "time": "2018-11-14 11:52"
        }, {
            "total_fund": -166098.087208,
            "incomes": 9558.436098,
            "outputs": 175656.523306,
            "time": "2018-11-14 11:53"
        }, {
            "total_fund": 175733.35926,
            "incomes": 257805.309745,
            "outputs": 82071.950485,
            "time": "2018-11-14 11:54"
        }, {
            "total_fund": 1353.372731,
            "incomes": 7286.795562,
            "outputs": 5933.422831,
            "time": "2018-11-14 11:55"
        }, {
            "total_fund": -118298.116031,
            "incomes": 22378.35695,
            "outputs": 140676.472981,
            "time": "2018-11-14 12:00"
        }, {
            "total_fund": 240041.830762,
            "incomes": 242318.778605,
            "outputs": 2276.947843,
            "time": "2018-11-14 12:01"
        }, {
            "total_fund": -78632.671,
            "incomes": 19634.710272,
            "outputs": 98267.381272,
            "time": "2018-11-14 12:02"
        }, {
            "total_fund": 38179.616252,
            "incomes": 38250.025225,
            "outputs": 70.408973,
            "time": "2018-11-14 12:03"
        }, {
            "total_fund": -165192.98673,
            "incomes": 55.557329,
            "outputs": 165248.544059,
            "time": "2018-11-14 12:04"
        }, {
            "total_fund": -36073.103391,
            "incomes": 211.893491,
            "outputs": 36284.996882,
            "time": "2018-11-14 12:05"
        }, {
            "total_fund": -396.606967,
            "incomes": 89.149637,
            "outputs": 485.756604,
            "time": "2018-11-14 12:06"
        }, {
            "total_fund": 58.806753,
            "incomes": 302.3163,
            "outputs": 243.509547,
            "time": "2018-11-14 12:07"
        }, {
            "total_fund": 52625.081774,
            "incomes": 54103.575739,
            "outputs": 1478.493965,
            "time": "2018-11-14 12:08"
        }, {
            "total_fund": -25281.667416,
            "incomes": 3141.031966,
            "outputs": 28422.699382,
            "time": "2018-11-14 12:09"
        }, {
            "total_fund": 21453.670423,
            "incomes": 82494.468224,
            "outputs": 61040.797801,
            "time": "2018-11-14 12:10"
        }, {
            "total_fund": -8841.09834,
            "incomes": 1193.628559,
            "outputs": 10034.726899,
            "time": "2018-11-14 12:11"
        }, {
            "total_fund": -37874.95167,
            "incomes": 16246.623772,
            "outputs": 54121.575442,
            "time": "2018-11-14 12:12"
        }, {
            "total_fund": -91063.112487,
            "incomes": 594.425481,
            "outputs": 91657.537968,
            "time": "2018-11-14 12:13"
        }, {
            "total_fund": -8438.915378,
            "incomes": 14494.685313,
            "outputs": 22933.600691,
            "time": "2018-11-14 12:14"
        }, {
            "total_fund": 239248.51148543,
            "incomes": 247300.48790243,
            "outputs": 8051.976417,
            "time": "2018-11-14 12:15"
        }, {
            "total_fund": -80499.591506,
            "incomes": 11489.781573,
            "outputs": 91989.373079,
            "time": "2018-11-14 12:16"
        }, {
            "total_fund": 76169.549977,
            "incomes": 84124.88225,
            "outputs": 7955.332273,
            "time": "2018-11-14 12:17"
        }, {
            "total_fund": -11920.693645,
            "incomes": 31424.398826,
            "outputs": 43345.092471,
            "time": "2018-11-14 12:18"
        }, {
            "total_fund": 9025.195824,
            "incomes": 37558.869021,
            "outputs": 28533.673197,
            "time": "2018-11-14 12:19"
        }, {
            "total_fund": -6187.0141,
            "incomes": 472.883564,
            "outputs": 6659.897664,
            "time": "2018-11-14 12:20"
        }, {
            "total_fund": 60083.87522,
            "incomes": 60949.373846,
            "outputs": 865.498626,
            "time": "2018-11-14 12:21"
        }, {
            "total_fund": -193026.428053,
            "incomes": 318.027491,
            "outputs": 193344.455544,
            "time": "2018-11-14 12:22"
        }, {
            "total_fund": -1166.15979529,
            "incomes": 3402.46421571,
            "outputs": 4568.624011,
            "time": "2018-11-14 12:23"
        }, {
            "total_fund": -71333.829636,
            "incomes": 23213.482419,
            "outputs": 94547.312055,
            "time": "2018-11-14 12:24"
        }, {
            "total_fund": 74382.307788,
            "incomes": 84177.95029,
            "outputs": 9795.642502,
            "time": "2018-11-14 12:25"
        }, {
            "total_fund": 63979.140397,
            "incomes": 94184.058162,
            "outputs": 30204.917765,
            "time": "2018-11-14 12:26"
        }, {
            "total_fund": -98367.570626,
            "incomes": 2868.820524,
            "outputs": 101236.39115,
            "time": "2018-11-14 12:27"
        }, {
            "total_fund": 30886.735561,
            "incomes": 92321.968961,
            "outputs": 61435.2334,
            "time": "2018-11-14 12:28"
        }, {
            "total_fund": -77900.083527,
            "incomes": 142.850372,
            "outputs": 78042.933899,
            "time": "2018-11-14 12:29"
        }, {
            "total_fund": 79490.784881,
            "incomes": 80271.548592,
            "outputs": 780.763711,
            "time": "2018-11-14 12:30"
        }, {
            "total_fund": -12401.95792,
            "incomes": 50458.984084,
            "outputs": 62860.942004,
            "time": "2018-11-14 12:31"
        }, {
            "total_fund": -82563.047661,
            "incomes": 484.050978,
            "outputs": 83047.098639,
            "time": "2018-11-14 12:32"
        }, {
            "total_fund": 88427.413959,
            "incomes": 92847.882158,
            "outputs": 4420.468199,
            "time": "2018-11-14 12:33"
        }, {
            "total_fund": -6758.02342,
            "incomes": 339.293682,
            "outputs": 7097.317102,
            "time": "2018-11-14 12:34"
        }, {
            "total_fund": 1975.377749,
            "incomes": 2098.191661,
            "outputs": 122.813912,
            "time": "2018-11-14 12:35"
        }, {
            "total_fund": -4610.495842,
            "incomes": 0.64639,
            "outputs": 4611.142232,
            "time": "2018-11-14 12:36"
        }, {
            "total_fund": 74699.994003,
            "incomes": 101499.9026,
            "outputs": 26799.908597,
            "time": "2018-11-14 12:37"
        }, {
            "total_fund": -26676.566921,
            "incomes": 219.74463,
            "outputs": 26896.311551,
            "time": "2018-11-14 12:38"
        }, {
            "total_fund": -106967.735682,
            "incomes": 26.497009,
            "outputs": 106994.232691,
            "time": "2018-11-14 12:39"
        }, {
            "total_fund": -6569.259831,
            "incomes": 85.306884,
            "outputs": 6654.566715,
            "time": "2018-11-14 12:40"
        }, {
            "total_fund": 83812.670622,
            "incomes": 89994.079763,
            "outputs": 6181.409141,
            "time": "2018-11-14 12:41"
        }, {
            "total_fund": 119721.584312,
            "incomes": 121961.494666,
            "outputs": 2239.910354,
            "time": "2018-11-14 12:42"
        }, {
            "total_fund": 94754.957155,
            "incomes": 96461.122125,
            "outputs": 1706.16497,
            "time": "2018-11-14 12:43"
        }, {
            "total_fund": -77572.250395,
            "incomes": 11021.060579,
            "outputs": 88593.310974,
            "time": "2018-11-14 12:44"
        }, {
            "total_fund": 202757.819372,
            "incomes": 204719.206489,
            "outputs": 1961.387117,
            "time": "2018-11-14 12:45"
        }, {
            "total_fund": 53107.081421,
            "incomes": 57797.339744,
            "outputs": 4690.258323,
            "time": "2018-11-14 12:46"
        }, {
            "total_fund": -53830.007234,
            "incomes": 46492.386101,
            "outputs": 100322.393335,
            "time": "2018-11-14 12:47"
        }, {
            "total_fund": 26059.644182,
            "incomes": 120075.982298,
            "outputs": 94016.338116,
            "time": "2018-11-14 12:48"
        }, {
            "total_fund": 83750.592652,
            "incomes": 120950.81782,
            "outputs": 37200.225168,
            "time": "2018-11-14 12:49"
        }, {
            "total_fund": -132821.506347,
            "incomes": 460.165826,
            "outputs": 133281.672173,
            "time": "2018-11-14 12:50"
        }, {
            "total_fund": -71450.174377,
            "incomes": 4208.907549,
            "outputs": 75659.081926,
            "time": "2018-11-14 12:51"
        }, {
            "total_fund": 15882.164209,
            "incomes": 93554.393096,
            "outputs": 77672.228887,
            "time": "2018-11-14 12:52"
        }, {
            "total_fund": 36274.711316,
            "incomes": 97135.636783,
            "outputs": 60860.925467,
            "time": "2018-11-14 12:53"
        }, {
            "total_fund": 138976.78944,
            "incomes": 141585.574495,
            "outputs": 2608.785055,
            "time": "2018-11-14 12:54"
        }, {
            "total_fund": 36977.385688,
            "incomes": 40416.413498,
            "outputs": 3439.02781,
            "time": "2018-11-14 12:55"
        }, {
            "total_fund": 33551.576834,
            "incomes": 93707.384309,
            "outputs": 60155.807475,
            "time": "2018-11-14 12:56"
        }, {
            "total_fund": 38346.398931,
            "incomes": 90780.658591,
            "outputs": 52434.25966,
            "time": "2018-11-14 12:57"
        }, {
            "total_fund": 3148.884706,
            "incomes": 5796.452997,
            "outputs": 2647.568291,
            "time": "2018-11-14 12:58"
        }, {
            "total_fund": -164480.730322,
            "incomes": 25082.553157,
            "outputs": 189563.283479,
            "time": "2018-11-14 12:59"
        }, {
            "total_fund": 57791.291141,
            "incomes": 129799.938093,
            "outputs": 72008.646952,
            "time": "2018-11-14 13:00"
        }, {
            "total_fund": 283236.136202,
            "incomes": 283578.673612,
            "outputs": 342.53741,
            "time": "2018-11-14 13:01"
        }, {
            "total_fund": 25536.298695,
            "incomes": 34775.512736,
            "outputs": 9239.214041,
            "time": "2018-11-14 13:02"
        }, {
            "total_fund": -92416.967157,
            "incomes": 2377.17494,
            "outputs": 94794.142097,
            "time": "2018-11-14 13:03"
        }, {
            "total_fund": 171.915546,
            "incomes": 548.700867,
            "outputs": 376.785321,
            "time": "2018-11-14 13:04"
        }, {
            "total_fund": 119158.941963,
            "incomes": 119458.82816,
            "outputs": 299.886197,
            "time": "2018-11-14 13:05"
        }, {
            "total_fund": -31076.393583,
            "incomes": 383.280687,
            "outputs": 31459.67427,
            "time": "2018-11-14 13:06"
        }, {
            "total_fund": -266730.26783401,
            "incomes": 19247.244741986,
            "outputs": 285977.512576,
            "time": "2018-11-14 13:07"
        }, {
            "total_fund": 64972.843073,
            "incomes": 64979.306912,
            "outputs": 6.463839,
            "time": "2018-11-14 13:08"
        }, {
            "total_fund": 73036.729959,
            "incomes": 79549.41539,
            "outputs": 6512.685431,
            "time": "2018-11-14 13:09"
        }, {
            "total_fund": -2939.12816,
            "incomes": 3362.32792,
            "outputs": 6301.45608,
            "time": "2018-11-14 13:10"
        }, {
            "total_fund": -96240.550955,
            "incomes": 7414.024293,
            "outputs": 103654.575248,
            "time": "2018-11-14 13:11"
        }, {
            "total_fund": -74779.637986,
            "incomes": 13.576641,
            "outputs": 74793.214627,
            "time": "2018-11-14 13:12"
        }, {
            "total_fund": 4819.909524,
            "incomes": 98343.838185,
            "outputs": 93523.928661,
            "time": "2018-11-14 13:13"
        }, {
            "total_fund": -39706.956905,
            "incomes": 18926.295597,
            "outputs": 58633.252502,
            "time": "2018-11-14 13:14"
        }, {
            "total_fund": 28201.77798,
            "incomes": 30364.905403,
            "outputs": 2163.127423,
            "time": "2018-11-14 13:15"
        }, {
            "total_fund": -350.359974,
            "incomes": 752.185097,
            "outputs": 1102.545071,
            "time": "2018-11-14 13:16"
        }, {
            "total_fund": 97700.65216,
            "incomes": 100285.80016,
            "outputs": 2585.148,
            "time": "2018-11-14 13:17"
        }, {
            "total_fund": -35750.703075,
            "incomes": 61729.349182,
            "outputs": 97480.052257,
            "time": "2018-11-14 13:18"
        }, {
            "total_fund": 81148.786314,
            "incomes": 84530.908238,
            "outputs": 3382.121924,
            "time": "2018-11-14 13:19"
        }, {
            "total_fund": 70918.832956,
            "incomes": 72870.4471,
            "outputs": 1951.614144,
            "time": "2018-11-14 13:20"
        }, {
            "total_fund": -302464.891688,
            "incomes": 55776.157315,
            "outputs": 358241.049003,
            "time": "2018-11-14 13:21"
        }, {
            "total_fund": -7146.449834,
            "incomes": 77915.986217,
            "outputs": 85062.436051,
            "time": "2018-11-14 13:22"
        }, {
            "total_fund": 50592.885633,
            "incomes": 53163.224073,
            "outputs": 2570.33844,
            "time": "2018-11-14 13:23"
        }, {
            "total_fund": 1068.217821,
            "incomes": 2666.818,
            "outputs": 1598.600179,
            "time": "2018-11-14 13:24"
        }, {
            "total_fund": -7836.250235,
            "incomes": 2771.872745,
            "outputs": 10608.12298,
            "time": "2018-11-14 13:25"
        }, {
            "total_fund": -83683.469946,
            "incomes": 1.29193,
            "outputs": 83684.761876,
            "time": "2018-11-14 13:26"
        }, {
            "total_fund": -52098.112020139,
            "incomes": 7882.6140258613,
            "outputs": 59980.726046,
            "time": "2018-11-14 13:27"
        }, {
            "total_fund": 32577.979581861,
            "incomes": 34315.950753861,
            "outputs": 1737.971172,
            "time": "2018-11-14 13:28"
        }, {
            "total_fund": -71604.943977,
            "incomes": 3839.867567,
            "outputs": 75444.811544,
            "time": "2018-11-14 13:29"
        }, {
            "total_fund": -82649.315527737,
            "incomes": 4263.7481912628,
            "outputs": 86913.063719,
            "time": "2018-11-14 13:30"
        }, {
            "total_fund": -120475.229634,
            "incomes": 1389.004962,
            "outputs": 121864.234596,
            "time": "2018-11-14 13:31"
        }, {
            "total_fund": 63477.991434,
            "incomes": 147695.6362,
            "outputs": 84217.644766,
            "time": "2018-11-14 13:32"
        }, {
            "total_fund": 22116.494538,
            "incomes": 108301.556453,
            "outputs": 86185.061915,
            "time": "2018-11-14 13:33"
        }, {
            "total_fund": -10.986485,
            "incomes": 68.50513,
            "outputs": 79.491615,
            "time": "2018-11-14 13:34"
        }, {
            "total_fund": -86870.833745,
            "incomes": 38112.536171,
            "outputs": 124983.369916,
            "time": "2018-11-14 13:35"
        }, {
            "total_fund": 55756.947972,
            "incomes": 166167.431157,
            "outputs": 110410.483185,
            "time": "2018-11-14 13:36"
        }, {
            "total_fund": 547.618326,
            "incomes": 755.156382,
            "outputs": 207.538056,
            "time": "2018-11-14 13:37"
        }, {
            "total_fund": -75789.995843,
            "incomes": 6462.805018,
            "outputs": 82252.800861,
            "time": "2018-11-14 13:38"
        }, {
            "total_fund": 29911.901402,
            "incomes": 30513.242192,
            "outputs": 601.34079,
            "time": "2018-11-14 13:39"
        }, {
            "total_fund": 240627.212303,
            "incomes": 251783.490345,
            "outputs": 11156.278042,
            "time": "2018-11-14 13:40"
        }, {
            "total_fund": -31545.203035,
            "incomes": 30022.432225,
            "outputs": 61567.63526,
            "time": "2018-11-14 13:41"
        }, {
            "total_fund": -102384.001139,
            "incomes": 70306.659437,
            "outputs": 172690.660576,
            "time": "2018-11-14 13:42"
        }, {
            "total_fund": -129589.081178,
            "incomes": 3982.731189,
            "outputs": 133571.812367,
            "time": "2018-11-14 13:43"
        }, {
            "total_fund": 36258.768698,
            "incomes": 53165.086128,
            "outputs": 16906.31743,
            "time": "2018-11-14 13:44"
        }, {
            "total_fund": -957.611337,
            "incomes": 1422.836357,
            "outputs": 2380.447694,
            "time": "2018-11-14 13:45"
        }, {
            "total_fund": 12453.133019,
            "incomes": 13747.854056,
            "outputs": 1294.721037,
            "time": "2018-11-14 13:46"
        }, {
            "total_fund": -540.408215,
            "incomes": 2204.430526,
            "outputs": 2744.838741,
            "time": "2018-11-14 13:47"
        }, {
            "total_fund": -11154.629884,
            "incomes": 62638.871334,
            "outputs": 73793.501218,
            "time": "2018-11-14 13:48"
        }, {
            "total_fund": 10068.08116,
            "incomes": 13307.636474,
            "outputs": 3239.555314,
            "time": "2018-11-14 13:49"
        }, {
            "total_fund": 20208.036551,
            "incomes": 25165.357382,
            "outputs": 4957.320831,
            "time": "2018-11-14 13:50"
        }, {
            "total_fund": 101128.950427,
            "incomes": 104041.584977,
            "outputs": 2912.63455,
            "time": "2018-11-14 13:51"
        }, {
            "total_fund": 120138.214693,
            "incomes": 120437.815144,
            "outputs": 299.600451,
            "time": "2018-11-14 13:52"
        }]
    }
}
